<?xml version="1.0" encoding="utf-8"?><SpellingWordList xmlns:xsi="http://www.w3.org/2001/XMLSchema-instance" xmlns:xsd="http://www.w3.org/2001/XMLSchema"><ListName>Grade 6 List 1</ListName><Words><SpellingWord><Word>accept</Word><Prompt>I can't %% that The Flash might be Santa Claus.</Prompt></SpellingWord><SpellingWord><Word>ancient</Word><Prompt>The %% Egyptians really liked cats.</Prompt></SpellingWord><SpellingWord><Word>audience</Word><Prompt>The %% laughed at the comedian's jokes.</Prompt></SpellingWord><SpellingWord><Word>blown</Word><Prompt>I was %% away by that action sequence.</Prompt></SpellingWord><SpellingWord><Word>canyon</Word><Prompt>The grand %% is just a really big hole.</Prompt></SpellingWord><SpellingWord><Word>ceiling</Word><Prompt>Don't throw sharpened pencils at the %%.</Prompt></SpellingWord><SpellingWord><Word>combination</Word><Prompt>The %% of peanut butter and jelly is surprisingly good.</Prompt></SpellingWord><SpellingWord><Word>concentration</Word><Prompt>Driving on the interstate requires a lot of %%.</Prompt></SpellingWord><SpellingWord><Word>contagious</Word><Prompt>The flu is very %%.</Prompt></SpellingWord><SpellingWord><Word>coupon</Word><Prompt>I used a %% to save ten percent.</Prompt></SpellingWord><SpellingWord><Word>culture</Word><Prompt>American %% is all about big stuff and explosions.</Prompt></SpellingWord><SpellingWord><Word>demonstrate</Word><Prompt>Allow me to %% my uppercut on this punching bag.</Prompt></SpellingWord><SpellingWord><Word>depth</Word><Prompt>He went in %% about why he thinks water isn't wet.</Prompt></SpellingWord><SpellingWord><Word>discussion</Word><Prompt>After a lengthy %%, we decided that Captain America should've been promoted to Major.</Prompt></SpellingWord><SpellingWord><Word>echoes</Word><Prompt>Your voice %% in a canyon.  Or somebody on the other side is just repeating what you said.</Prompt></SpellingWord></Words><GradeLevel>0</GradeLevel></SpellingWordList>